dpc/__init__.py
dpc/base.py
dpc/d.py
dpc/ef.py
dpc/ff1.py
dpc/h.py
tests/__init__.py
tests/test_base.py
tests/test_ef.py
dpc_python-0.1.0.dist-info/LICENSE
dpc_python-0.1.0.dist-info/METADATA
dpc_python-0.1.0.dist-info/WHEEL
dpc_python-0.1.0.dist-info/top_level.txt
dpc_python-0.1.0.dist-info/RECORD
