Metadata-Version: 2.1
Name: dpc-python
Version: 0.1.0
Summary: A library for handling DPC data
Home-page: https://github.com/setomits/dpc-python
Author: Mitsuhiro Setoguchi
Author-email: setomits@gmail.com
Classifier: Programming Language :: Python :: 3
Classifier: License :: OSI Approved :: MIT License
Classifier: Operating System :: OS Independent
Requires-Python: >=3.7
License-File: LICENSE
